odoo/addons/stock_orderpoint_mto_as_mts/README.rst
odoo/addons/stock_orderpoint_mto_as_mts/__init__.py
odoo/addons/stock_orderpoint_mto_as_mts/__manifest__.py
odoo/addons/stock_orderpoint_mto_as_mts/i18n/fr.po
odoo/addons/stock_orderpoint_mto_as_mts/i18n/it.po
odoo/addons/stock_orderpoint_mto_as_mts/i18n/stock_orderpoint_mto_as_mts.pot
odoo/addons/stock_orderpoint_mto_as_mts/i18n/tr.po
odoo/addons/stock_orderpoint_mto_as_mts/models/__init__.py
odoo/addons/stock_orderpoint_mto_as_mts/models/product_category.py
odoo/addons/stock_orderpoint_mto_as_mts/models/product_product.py
odoo/addons/stock_orderpoint_mto_as_mts/models/product_template.py
odoo/addons/stock_orderpoint_mto_as_mts/models/stock_route.py
odoo/addons/stock_orderpoint_mto_as_mts/models/stock_warehouse.py
odoo/addons/stock_orderpoint_mto_as_mts/readme/CONFIGURATION.md
odoo/addons/stock_orderpoint_mto_as_mts/readme/CONTRIBUTORS.md
odoo/addons/stock_orderpoint_mto_as_mts/readme/CREDITS.md
odoo/addons/stock_orderpoint_mto_as_mts/readme/DESCRIPTION.md
odoo/addons/stock_orderpoint_mto_as_mts/readme/ROADMAP.md
odoo/addons/stock_orderpoint_mto_as_mts/static/description/icon.png
odoo/addons/stock_orderpoint_mto_as_mts/static/description/index.html
odoo/addons/stock_orderpoint_mto_as_mts/tests/__init__.py
odoo/addons/stock_orderpoint_mto_as_mts/tests/test_stock_orderpoint_mto_as_mts.py
odoo/addons/stock_orderpoint_mto_as_mts/tests/test_stock_warehouse_mto_as_mts.py
odoo/addons/stock_orderpoint_mto_as_mts/views/stock_warehouse_views.xml
odoo_addon_stock_orderpoint_mto_as_mts-18.0.1.1.0.dist-info/METADATA
odoo_addon_stock_orderpoint_mto_as_mts-18.0.1.1.0.dist-info/WHEEL
odoo_addon_stock_orderpoint_mto_as_mts-18.0.1.1.0.dist-info/top_level.txt
odoo_addon_stock_orderpoint_mto_as_mts-18.0.1.1.0.dist-info/RECORD
