Metadata-Version: 2.1
Name: odoo-addon-stock_orderpoint_mto_as_mts
Version: 18.0.1.1.0
Requires-Python: >=3.10
Requires-Dist: odoo-addon-base_partition==18.0.*
Requires-Dist: odoo-addon-product_route_mto==18.0.*
Requires-Dist: odoo-addon-stock_orderpoint_default_location==18.0.*
Requires-Dist: odoo==18.0.*
Summary: Materialize need from MTO route through orderpoint
Home-page: https://github.com/OCA/stock-logistics-orderpoint
License: AGPL-3
Author: BCIM, Camptocamp, Odoo Community Association (OCA)
Author-email: support@odoo-community.org
Classifier: Programming Language :: Python
Classifier: Framework :: Odoo
Classifier: Framework :: Odoo :: 18.0
Classifier: License :: OSI Approved :: GNU Affero General Public License v3
Classifier: Development Status :: 3 - Alpha
